{
    "id": "61c6670d-b326-4238-a3c2-334dcb8cbe47",
    "nom": "Jan Turon Pau",
    "email": "jthec0001@gmail.com",
    "telefon": "665412479",
    "password_enc": "Z6BcMnvW2WNISxaYfTA9ODo6OFBlbHJiUG1Qdk1taStUUFBDZmR3dz09",
    "ruta": "curta",
    "motivacio": "Mai l'he fet",
    "created_at": "2026-03-21T21:50:51+01:00",
    "checkins": [
        {
            "parada_id": 3,
            "timestamp": "2026-03-22T00:55:33+01:00"
        },
        {
            "parada_id": 4,
            "timestamp": "2026-03-22T00:55:37+01:00"
        },
        {
            "parada_id": 5,
            "timestamp": "2026-03-22T05:39:29+01:00",
            "test": {
                "p1": "Bé",
                "p2": "Increïble",
                "p3": "Retirada"
            }
        },
        {
            "parada_id": 6,
            "timestamp": "2026-03-22T05:40:13+01:00",
            "test": {
                "p1": "Incredul\/a",
                "p2": "100% sí",
                "p3": "Deixat veure"
            }
        },
        {
            "parada_id": 7,
            "timestamp": "2026-03-22T05:41:16+01:00",
            "test": {
                "p1": "Estic volant",
                "p2": "Sí, molt",
                "p3": "Poc a poc, s&#039;omple el pot"
            }
        },
        {
            "parada_id": 8,
            "timestamp": "2026-03-22T08:32:41+01:00",
            "test": {
                "p1": "Orgullós\/a",
                "p2": "Molts embenats",
                "p3": "Per mi, som durs"
            }
        },
        {
            "parada_id": 9,
            "timestamp": "2026-03-22T09:53:42+01:00",
            "test": {
                "p1": "A poc a poc però segur\/a",
                "p2": "Renovant",
                "p3": "Molta força mental"
            }
        }
    ],
    "share_location": false
}